{
    "backend": "flask",
    "db_name": "",
    "db_pass": "",
    "db_type": "",
    "db_user": "",
    "dbms": "0",
    "description": "generated product",
    "design": "soft-ui-dashboard",
    "docker": "0",
    "err_code": 0,
    "frontend": "",
    "heroku": "0",
    "pattern": "mvc",
    "pro": "0",
    "task_id": "6b732122-12ca-4aaa-92e3-05f47f1e838f",
    "task_info": "Upload Sources [0%] - 319 files",
    "task_output": "6b732122-12ca-4aaa-92e3-05f47f1e838f.zip",
    "task_result": "SUCCESS",
    "task_state": "RUNNING",
    "task_ts_end": "2022-11-29-08-19-43",
    "task_ts_start": "2022-11-29-08-19-40"
}